MANIFEST.in
README.txt
setup.cfg
setup.py
docs/news.txt
docs/recipe.txt
gp/__init__.py
gp.vcsdevelop.egg-info/PKG-INFO
gp.vcsdevelop.egg-info/SOURCES.txt
gp.vcsdevelop.egg-info/dependency_links.txt
gp.vcsdevelop.egg-info/entry_points.txt
gp.vcsdevelop.egg-info/namespace_packages.txt
gp.vcsdevelop.egg-info/not-zip-safe
gp.vcsdevelop.egg-info/requires.txt
gp.vcsdevelop.egg-info/top_level.txt
gp/vcsdevelop/__init__.py
gp/vcsdevelop/get-pip.py
gp/vcsdevelop/get_pip.py
gp/vcsdevelop/tests.py