Metadata-Version: 1.0
Name: gp.vcsdevelop
Version: 2.2.2
Summary: ZC buildout extension to checkout eggs from various vcs
Home-page: http://www.gawel.org/docs/gp.vcsdevelop/index.html
Author: Gael Pasgrimaud
Author-email: gael@gawel.org
License: MIT
Keywords: buildout extension vcs develop
Platform: UNKNOWN
Classifier: Framework :: Buildout
Classifier: Intended Audience :: Developers
Classifier: License :: OSI Approved
Classifier: Development Status :: 5 - Production/Stable
Classifier: Programming Language :: Python :: 2
Classifier: Programming Language :: Python :: 3
